multidimensionalks/__init__.py
multidimensionalks/avx2.cpython-310-x86_64-linux-gnu.so
multidimensionalks/avx512.cpython-310-x86_64-linux-gnu.so
multidimensionalks/brute.cpython-310-x86_64-linux-gnu.so
multidimensionalks/brute_avx2.cpython-310-x86_64-linux-gnu.so
multidimensionalks/brute_avx512.cpython-310-x86_64-linux-gnu.so
multidimensionalks/pure.cpython-310-x86_64-linux-gnu.so
multidimensionalks.libs/libboost_system-ce6bbf35.so.1.53.0
multidimensionalks-0.2.21.dist-info/METADATA
multidimensionalks-0.2.21.dist-info/WHEEL
multidimensionalks-0.2.21.dist-info/top_level.txt
multidimensionalks-0.2.21.dist-info/RECORD
multidimensionalks-0.2.21.dist-info/licenses/LICENSE
