Metadata-Version: 2.4
Name: multidimensionalks
Version: 0.2.21
Summary: Multidimensional KS test module in python
Author: Tomasz Pawlowski
Author-email: tp292676@students.mimuw.edu.pl
License: MIT
Classifier: Development Status :: 2 - Pre-Alpha
Classifier: License :: OSI Approved :: MIT License
License-File: LICENSE
Requires-Dist: numpy>=1.19
Requires-Dist: cpufeature>=0.2.0
Dynamic: author
Dynamic: author-email
Dynamic: classifier
Dynamic: description
Dynamic: description-content-type
Dynamic: license
Dynamic: license-file
Dynamic: requires-dist
Dynamic: summary
